spaemis/__init__.py
spaemis/commands/__init__.py
spaemis/commands/base.py
spaemis/commands/generate_command.py
spaemis/commands/gse_emis_command.py
spaemis/commands/point_source_command.py
spaemis/config.py
spaemis/constants.py
spaemis/gse_emis.py
spaemis/input_data.py
spaemis/inventory.py
spaemis/main.py
spaemis/project.py
spaemis/py.typed
spaemis/scaling/__init__.py
spaemis/scaling/base.py
spaemis/scaling/constant.py
spaemis/scaling/exclude.py
spaemis/scaling/point_source.py
spaemis/scaling/proxy.py
spaemis/scaling/relative_change.py
spaemis/scaling/timeseries.py
spaemis/unit_registry.py
spaemis/utils.py
spaemis-0.2.3.dist-info/LICENSE
spaemis-0.2.3.dist-info/METADATA
spaemis-0.2.3.dist-info/WHEEL
spaemis-0.2.3.dist-info/entry_points.txt
spaemis-0.2.3.dist-info/RECORD
