Metadata-Version: 2.1
Name: spaemis
Version: 0.2.3
Summary: Produce a coherent set of emissions for regional air quality modelling
Home-page: https://github.com/climate-resource/spaemis
Keywords: emissions,climate,air quality
Author: Jared Lewis
Author-email: jared.lewis@climate-resource.com
Requires-Python: >=3.10,<3.12
Classifier: Development Status :: 4 - Beta
Classifier: Intended Audience :: Developers
Classifier: Intended Audience :: Science/Research
Classifier: License :: OSI Approved :: BSD License
Classifier: Operating System :: OS Independent
Classifier: Programming Language :: Python
Classifier: Programming Language :: Python :: 3
Classifier: Programming Language :: Python :: 3.10
Classifier: Programming Language :: Python :: 3.11
Classifier: Topic :: Scientific/Engineering
Provides-Extra: notebooks
Requires-Dist: cattrs (>=22.2.0,<23.0.0)
Requires-Dist: geopandas (>=0.13.0,<0.14.0)
Requires-Dist: jupytext (==1.14.5) ; extra == "notebooks"
Requires-Dist: matplotlib (>=3.7.1,<4.0.0) ; extra == "notebooks"
Requires-Dist: netcdf4 (>=1.6.3,<2.0.0)
Requires-Dist: notebook (>=6.5.3,<7.0.0) ; extra == "notebooks"
Requires-Dist: papermill ; extra == "notebooks"
Requires-Dist: pooch (>=1.7.0,<2.0.0)
Requires-Dist: python-dotenv ; extra == "notebooks"
Requires-Dist: pyyaml (>=6.0,<7.0)
Requires-Dist: rioxarray (>=0.14.1,<0.15.0)
Requires-Dist: scipy (>=1.10.1,<2.0.0)
Requires-Dist: scmdata (>=0.15.0,<0.16.0)
Requires-Dist: seaborn ; extra == "notebooks"
Requires-Dist: typing-extensions (>=4.5.0,<5.0.0)
Requires-Dist: xarray (>=2023.5.0,<2024.0.0)
